{
  "job_id": "6a78aa89-a9d3-4509-a772-dd337362c063",
  "analysis_results": {
    "NIFTY50": {
      "asset_type": "NIFTY50",
      "sentiment": 0.0,
      "confidence": 0.5,
      "execution_time": 0.0,
      "component_details": {},
      "market_context": {},
      "status": "success",
      "timestamp": "2025-09-08T19:39:10.175478",
      "data_source": "Multiple_Indian_APIs"
    },
    "GOLD": {
      "asset_type": "GOLD",
      "sentiment": 0.30091285642254045,
      "confidence": 0.7713333333333333,
      "execution_time": 33.208766,
      "component_details": {
        "technical_analysis": {
          "component_name": "Technical_Analysis",
          "sentiment": 1.0,
          "confidence": 0.71,
          "framework_weight": 0.25,
          "weighted_contribution": 0.25,
          "description": "Technical_Analysis analysis",
          "source": "Technical_Analysis",
          "metadata": {},
          "status": "success"
        },
        "real_interest_rates": {
          "component_name": "Real_Interest_Rates",
          "sentiment": 0.40285655414444405,
          "confidence": 0.75,
          "framework_weight": 0.25,
          "weighted_contribution": 0.10071413853611101,
          "description": "Bullish",
          "source": "Real_Interest_Rates",
          "metadata": {},
          "status": "success"
        },
        "central_bank_sentiment": {
          "component_name": "Central_Bank_Sentiment",
          "sentiment": 0.21795178986571184,
          "confidence": 0.58,
          "framework_weight": 0.2,
          "weighted_contribution": 0.04359035797314237,
          "description": "\ud83d\udfe1 MILDLY BULLISH - Some positive signals (ENHANCED DETECTION)",
          "source": "Central_Bank_Sentiment",
          "metadata": {},
          "status": "success"
        },
        "professional_positioning": {
          "component_name": "Professional_Positioning_COT",
          "sentiment": -0.018339851009173073,
          "confidence": 0.5,
          "framework_weight": 0.15,
          "weighted_contribution": -0.002750977651375961,
          "description": "COT proxy: Est. commercial position -1.2%",
          "source": "COT_Price_Proxy",
          "metadata": {
            "estimated_position": -1.223164311767649,
            "recent_return": 0.00855901830966459,
            "volume_factor": 1.4290941642062944,
            "method": "price_proxy",
            "note": "Estimated from price action - lower confidence"
          },
          "status": "success"
        },
        "currency_debasement": {
          "component_name": "Currency_Debasement_Risk",
          "sentiment": 0.04470717427233503,
          "confidence": 0.8166666666666668,
          "framework_weight": 0.1,
          "weighted_contribution": 0.004470717427233504,
          "description": "Currency debasement risk from 3 components",
          "source": "Currency_Debasement_Risk_Multi",
          "metadata": {
            "components_analyzed": 3,
            "component_details": [
              {
                "name": "DXY_USD_Index",
                "sentiment": 0.08074815224994358,
                "confidence": 0.85,
                "weight": 0.4,
                "contribution": 0.02745437176498082
              },
              {
                "name": "EM_Currency_Stress",
                "sentiment": 0.2614007653388489,
                "confidence": 0.85,
                "weight": 0.3,
                "contribution": 0.06665719516140646
              },
              {
                "name": "CB_Balance_Sheet_Expansion",
                "sentiment": -0.2553408178803225,
                "confidence": 0.75,
                "weight": 0.3,
                "contribution": -0.057451684023072554
              }
            ],
            "method": "multi_component_analysis",
            "component_weights": {
              "dxy": 0.4,
              "em_stress": 0.3,
              "cb_expansion": 0.3
            }
          },
          "status": "success"
        }
      },
      "market_context": {},
      "status": "success",
      "timestamp": "2025-09-08T19:39:15.123737",
      "data_source": "Multiple_Global_APIs"
    },
    "BITCOIN": {
      "asset_type": "BITCOIN",
      "sentiment": -0.06758002202498793,
      "confidence": 0.4938571588444891,
      "execution_time": 7.75359,
      "component_details": {
        "micro_momentum": {
          "component_name": "micro_momentum",
          "sentiment": 0.18444377818128113,
          "confidence": 0.7166666666666667,
          "framework_weight": 0.3,
          "weighted_contribution": 0.055333133454384335,
          "description": "Bitcoin Micro Momentum Analysis",
          "source": "Bitcoin_micro_momentum",
          "metadata": {
            "roc_features": {
              "f_roc1": 0.012,
              "f_roc5": 0.098,
              "roc1_pct": 0.0048,
              "roc5_pct": 0.0907
            },
            "momentum_indicators": {
              "f_macd_hist": 0.176,
              "f_rsi_distance": 0.398,
              "rsi_value": 57.97,
              "macd_hist_z": 1.762
            },
            "price_analysis": {
              "f_vwap_distance": 0.382,
              "current_price": 112136.4,
              "intraday_vwap": 111877.45,
              "volatility_1h": 0.0446
            }
          },
          "market_context": {
            "data_source": "Kraken_OHLC_1min",
            "data_quality": "high",
            "data_points": 401,
            "last_update": "2025-09-08T14:08:00+00:00",
            "price_currency": "USD"
          },
          "status": "success",
          "execution_time": 1.52356
        },
        "funding_basis": {
          "component_name": "funding_basis",
          "sentiment": -0.07364804509565805,
          "confidence": 0.4480861376720488,
          "framework_weight": 0.3,
          "weighted_contribution": -0.022094413528697412,
          "description": "Bitcoin Funding Basis Analysis",
          "source": "Bitcoin_funding_basis",
          "metadata": {
            "funding_analysis": {
              "funding_rate_8h": 0.0,
              "funding_rate_annual_pct": 0.0,
              "f_funding_contrarian": -0.0,
              "funding_interpretation": "Neutral - balanced positioning"
            },
            "basis_analysis": {
              "spot_price": 112136.4,
              "mark_price": 112164.5,
              "basis_bps": 2.51,
              "f_basis_stretch": -0.245,
              "basis_interpretation": "Fair value - futures aligned with spot"
            },
            "oi_analysis": {
              "current_oi": 7656171.0,
              "oi_change_5m": 0.0,
              "oi_z_score": 0.0,
              "f_oi_momentum": 0.0
            }
          },
          "market_context": {
            "data_source": "Kraken_Spot_Futures",
            "data_quality": "high",
            "oi_history_length": 1,
            "funding_frequency": "8_hours",
            "price_currency": "USD"
          },
          "status": "success",
          "execution_time": 2.234844
        },
        "liquidity": {
          "component_name": "liquidity",
          "sentiment": -0.024689622763599234,
          "confidence": 0.7016666666666667,
          "framework_weight": 0.2,
          "weighted_contribution": -0.004937924552719847,
          "description": "Bitcoin Liquidity Analysis",
          "source": "Bitcoin_liquidity",
          "metadata": {
            "spread_analysis": {
              "current_spread_bps": 0.01,
              "median_spread_bps": 0.01,
              "relative_spread": -0.0,
              "f_spread_improvement": 0.0,
              "spread_interpretation": "Very tight - excellent liquidity"
            },
            "slippage_analysis": {
              "buy_slippage_bps": 0.21,
              "sell_slippage_bps": 0.0,
              "average_impact_bps": 0.11,
              "median_impact_bps": 0.11,
              "f_impact_improvement": 0.0,
              "standard_trade_size": 250000
            },
            "depth_analysis": {
              "bid_notional": 12697858.14,
              "ask_notional": 14377647.87,
              "depth_imbalance": -0.062,
              "f_imbalance": -0.123,
              "band_bps": 25
            }
          },
          "market_context": {
            "data_source": "Kraken_OrderBook",
            "data_quality": "high",
            "mid_price": 112136.35,
            "depth_levels_analyzed": 400,
            "spread_history_length": 1,
            "impact_history_length": 1,
            "price_currency": "USD"
          },
          "status": "success",
          "execution_time": 1.424774
        },
        "orderflow": {
          "component_name": "orderflow",
          "sentiment": -0.3904293876688315,
          "confidence": 0.8333333333333334,
          "framework_weight": 0.2,
          "weighted_contribution": -0.0780858775337663,
          "description": "Bitcoin Orderflow Analysis",
          "source": "Bitcoin_orderflow",
          "metadata": {
            "imbalance_analysis": {
              "imbalance_5m": 0.015,
              "buy_notional_5m": 173997.89,
              "sell_notional_5m": 168892.3,
              "total_notional_5m": 342890.18,
              "f_imb5": 0.021,
              "imbalance_interpretation": "Balanced flow - neutral"
            },
            "cvd_analysis": {
              "cvd_slope_15m": -298350.64,
              "cvd_scale": 94.39,
              "f_cvd15": -1.0,
              "cvd_current": -627339.93,
              "cvd_interpretation": "Strong cumulative selling"
            },
            "intensity_analysis": {
              "imbalance_1m": -0.73,
              "trades_1m": 31,
              "trade_rate_z": 0.0,
              "f_intensity": -0.0,
              "mean_trade_rate": 31.0
            }
          },
          "market_context": {
            "data_source": "Kraken_Trades",
            "data_quality": "high",
            "minute_buckets": 30,
            "trade_rate_history_length": 1,
            "data_timespan_minutes": 120,
            "price_currency": "USD"
          },
          "status": "success",
          "execution_time": 2.569581
        }
      },
      "executive_summary": {
        "overall_sentiment": -0.06758002202498793,
        "confidence_level": 0.4938571588444891,
        "interpretation": "\u26aa NEUTRAL - Balanced crypto signals",
        "risk_assessment": "HIGH RISK - Low confidence signals",
        "components_analyzed": 4,
        "recommendation": "Confidence Level: 49% - HIGH RISK - Low confidence signals"
      },
      "market_context": {
        "asset_type": "cryptocurrency",
        "data_source": "Kraken_Multi_API",
        "data_freshness": "real_time",
        "update_frequency": "1_minute",
        "price_currency": "USD"
      },
      "status": "success",
      "timestamp": "2025-09-08T19:38:55.310067",
      "data_source": "Kraken_Multi_API"
    },
    "REIT": {
      "asset_type": "REIT",
      "sentiment": -0.3729211412816436,
      "confidence": 0.8,
      "execution_time": 5.199413,
      "component_details": {
        "technical_momentum": {
          "component_name": "technical_momentum",
          "sentiment": -0.229307811680927,
          "confidence": 0.8,
          "framework_weight": 0.35,
          "weighted_contribution": -0.08025773408832444,
          "description": "REIT Technical Momentum Analysis - Original Logic",
          "source": "REIT_technical_momentum_Original",
          "metadata": {
            "original_diagnostics": {
              "score": -0.229,
              "features": {
                "f_roc20": 0.158,
                "f_rsi14": -0.214,
                "f_emaAlignSlope": -0.762
              },
              "metrics": {
                "price": 757.5,
                "roc20": 0.0138,
                "rsi14": 44.65
              }
            },
            "technical_features": {
              "f_roc20": 0.158,
              "f_rsi14": -0.214,
              "f_emaAlignSlope": -0.762
            },
            "price_metrics": {
              "price": 757.5,
              "roc20": 0.0138,
              "rsi14": 44.65
            }
          },
          "market_context": {
            "symbol": "DLF.NS",
            "data_source": "Yahoo_Finance_Original_Logic",
            "data_quality": "high",
            "price_currency": "INR"
          },
          "status": "success",
          "execution_time": 0.377655
        },
        "yield_spread": {
          "component_name": "yield_spread",
          "sentiment": -0.99999999975714,
          "confidence": 0.8,
          "framework_weight": 0.3,
          "weighted_contribution": -0.299999999927142,
          "description": "REIT Yield Spread Analysis - Original Logic",
          "source": "REIT_yield_spread_Original",
          "metadata": {
            "original_diagnostics": {
              "score": -1.0,
              "features": {
                "spread_frac": -0.0571,
                "reit_yield_ttm": 0.0079,
                "gsec10y_yield": 0.065
              },
              "metrics": {
                "div_ttm": 6.0,
                "price": 757.5,
                "scale_proxy": 0.001
              }
            },
            "yield_features": {
              "spread_frac": -0.0571,
              "reit_yield_ttm": 0.0079,
              "gsec10y_yield": 0.065
            },
            "yield_metrics": {
              "div_ttm": 6.0,
              "price": 757.5,
              "scale_proxy": 0.001
            }
          },
          "market_context": {
            "symbol": "DLF.NS",
            "data_source": "Yahoo_Finance_TradingEconomics_Original_Logic",
            "yield_anchor": "assumed_6.5%",
            "data_quality": "high",
            "price_currency": "INR"
          },
          "status": "success",
          "execution_time": 4.192236
        },
        "accumulation_flow": {
          "component_name": "accumulation_flow",
          "sentiment": -0.15743742995101792,
          "confidence": 0.8,
          "framework_weight": 0.2,
          "weighted_contribution": -0.03148748599020359,
          "description": "REIT Accumulation Flow Analysis - Original Logic",
          "source": "REIT_accumulation_flow_Original",
          "metadata": {
            "original_diagnostics": {
              "score": -0.157,
              "features": {
                "f_updown": -0.119,
                "f_ad_slope": -0.288,
                "f_obv_slope": -0.015
              },
              "metrics": {
                "up_down_ratio_20d": 0.964,
                "ad_slope_20d": -6388821.67,
                "obv_slope_20d": -706258.0
              }
            },
            "flow_features": {
              "f_updown": -0.119,
              "f_ad_slope": -0.288,
              "f_obv_slope": -0.015
            },
            "flow_metrics": {
              "up_down_ratio_20d": 0.964,
              "ad_slope_20d": -6388821.67,
              "obv_slope_20d": -706258.0
            }
          },
          "market_context": {
            "symbol": "DLF.NS",
            "data_source": "Yahoo_Finance_Original_Logic",
            "data_quality": "high",
            "price_currency": "INR"
          },
          "status": "success",
          "execution_time": 0.324069
        },
        "liquidity_risk": {
          "component_name": "liquidity_risk",
          "sentiment": 0.2588271914935093,
          "confidence": 0.8,
          "framework_weight": 0.15,
          "weighted_contribution": 0.03882407872402639,
          "description": "REIT Liquidity Risk Analysis - Original Logic",
          "source": "REIT_liquidity_risk_Original",
          "metadata": {
            "original_diagnostics": {
              "score": 0.259,
              "features": {
                "f_spread_proxy": 0.911,
                "f_amihud": -0.394
              },
              "metrics": {
                "range_today": 0.01281,
                "median_range_60d": 0.02078,
                "amihud_20d": 0.0
              }
            },
            "liquidity_features": {
              "f_spread_proxy": 0.911,
              "f_amihud": -0.394
            },
            "liquidity_metrics": {
              "range_today": 0.01281,
              "median_range_60d": 0.02078,
              "amihud_20d": 0.0
            }
          },
          "market_context": {
            "symbol": "DLF.NS",
            "data_source": "Yahoo_Finance_Original_Logic",
            "data_quality": "high",
            "price_currency": "INR"
          },
          "status": "success",
          "execution_time": 0.30481
        }
      },
      "executive_summary": {
        "overall_sentiment": -0.3729211412816436,
        "confidence_level": 0.8,
        "interpretation": "Bearish \u2014 mild",
        "components_analyzed": 4,
        "original_logic_preserved": true
      },
      "market_context": {
        "asset_type": "real_estate_investment_trust",
        "data_source": "Yahoo_Finance_TradingEconomics_Original_Logic",
        "data_freshness": "daily",
        "update_frequency": "daily",
        "price_currency": "INR",
        "logic_source": "friend_original_mindspace_code"
      },
      "symbol": "MINDSPACE",
      "status": "success",
      "timestamp": "2025-09-08T19:39:00.536731",
      "data_source": "Yahoo_Finance_TradingEconomics"
    }
  },
  "portfolio_summary": {
    "portfolio_sentiment": -0.035,
    "portfolio_confidence": 0.641,
    "successful_assets": 4,
    "failed_assets": 0,
    "total_assets": 4,
    "execution_time_seconds": 33.782445,
    "status": "success",
    "risk_assessment": "MODERATE RISK",
    "investment_recommendation": "HOLD",
    "asset_breakdown": {
      "NIFTY50": {
        "sentiment": 0.0,
        "confidence": 0.5,
        "status": "success"
      },
      "GOLD": {
        "sentiment": 0.301,
        "confidence": 0.771,
        "status": "success"
      },
      "BITCOIN": {
        "sentiment": -0.068,
        "confidence": 0.494,
        "status": "success"
      },
      "REIT": {
        "sentiment": -0.373,
        "confidence": 0.8,
        "status": "success"
      }
    }
  },
  "execution_time_seconds": 33.782445,
  "timestamp": "2025-09-08T19:39:15.123982",
  "assets_analyzed": 4,
  "total_assets_available": 4
}